CHANGES.txt
LICENSE.txt
MANIFEST.in
README.txt
setup.py
todo.txt
django_webcam_photoupload.egg-info/PKG-INFO
django_webcam_photoupload.egg-info/SOURCES.txt
django_webcam_photoupload.egg-info/dependency_links.txt
django_webcam_photoupload.egg-info/requires.txt
django_webcam_photoupload.egg-info/top_level.txt
photo_upload/__init__.py
photo_upload/admin.py
photo_upload/forms.py
photo_upload/models.py
photo_upload/settings.py
photo_upload/urls.py
photo_upload/views.py
photo_upload/wsgi.py
photo_upload/static/css/fileuploader.css
photo_upload/static/css/mixins.less
photo_upload/static/css/normalize.css
photo_upload/static/css/normalize.less
photo_upload/static/css/photo_upload.css
photo_upload/static/css/photo_upload.less
photo_upload/static/img/grey.gif
photo_upload/static/js/photo_upload.js
photo_upload/static/js/photo_upload_ie-ck.js
photo_upload/static/js/photo_upload_ie.js
photo_upload/static/js/libs/jquery-1.7.2.min-ck.js
photo_upload/static/js/libs/jquery-1.7.2.min.js
photo_upload/static/js/libs/modernizr-2.5.3.min-ck.js
photo_upload/static/js/libs/modernizr-2.5.3.min.js
photo_upload/static/js/plugins/fileuploader-ck.js
photo_upload/static/js/plugins/fileuploader.js
photo_upload/static/js/plugins/flash10canvas.swf
photo_upload/static/js/plugins/flash9canvas.swf
photo_upload/static/js/plugins/flashcanvas-ck.js
photo_upload/static/js/plugins/flashcanvas.js
photo_upload/static/js/plugins/jquery.form-ck.js
photo_upload/static/js/plugins/jquery.form.js
photo_upload/static/js/plugins/jquery.lazyload.min-ck.js
photo_upload/static/js/plugins/jquery.lazyload.min.js
photo_upload/static/js/plugins/spin.min-ck.js
photo_upload/static/js/plugins/spin.min.js
photo_upload/static/js/plugins/webcam-ck.js
photo_upload/static/js/plugins/webcam.js
photo_upload/static/logos/99percentmedia_logo.png
photo_upload/static/mp3/shutter.mp3
photo_upload/static/swf/webcam.swf
photo_upload/templates/base.html
photo_upload/templates/index.html
photo_upload/templates/list.html
ziplookup/__init__.py
ziplookup/load.py
ziplookup/models.py
ziplookup/urls.py
ziplookup/views.py
ziplookup/fixtures/initial_data.json