Metadata-Version: 1.0
Name: django-webcam-photoupload
Version: 0.3.3
Summary: Webcam photo uploads for the movement
Home-page: https://github.com/citizenengagementlab/django-webcam-photoupload
Author: Mike Vattuone
Author-email: mike.v@engagementlab.org
License: LICENSE.txt
Platform: UNKNOWN
